{"v":5,"entries":{"examples-multistyledinput--docs":{"id":"examples-multistyledinput--docs","title":"Examples/MultiStyledInput","name":"Docs","importPath":"./src/stories/MultiStyledInput.stories.ts","type":"docs","tags":["dev","test","autodocs"],"storiesImports":[]},"examples-multistyledinput--primary":{"type":"story","id":"examples-multistyledinput--primary","name":"Primary","title":"Examples/MultiStyledInput","importPath":"./src/stories/MultiStyledInput.stories.ts","componentPath":"./src/stories/MultiStyledInput.tsx","tags":["dev","test","autodocs"]}}}